igniteboot/__init__.py
igniteboot/app.py
igniteboot/auth.py
igniteboot/cli.py
igniteboot/config.py
igniteboot/events.py
igniteboot/models.py
igniteboot/plugin.py
igniteboot/route.py
igniteboot/server.py
igniteboot/session.py
igniteboot/templates.py
igniteboot/websocket.py
igniteboot/db/__init__.py
igniteboot/db/base.py
igniteboot/db/mysql.py
igniteboot/db/sqlite.py
igniteboot-0.1.1.dist-info/LICENSE
igniteboot-0.1.1.dist-info/METADATA
igniteboot-0.1.1.dist-info/WHEEL
igniteboot-0.1.1.dist-info/entry_points.txt
igniteboot-0.1.1.dist-info/top_level.txt
igniteboot-0.1.1.dist-info/RECORD
