Metadata-Version: 2.1
Name: igniteboot
Version: 0.1.1
Summary: A lightweight and modular Python backend framework
Home-page: https://github.com/m3r0n9/igniteboot
Author: m3r0n9
Author-email: your-email@example.com
License: MIT
Classifier: Programming Language :: Python :: 3
Classifier: License :: OSI Approved :: MIT License
Classifier: Operating System :: OS Independent
Requires-Python: >=3.7
License-File: LICENSE
Requires-Dist: fastapi
Requires-Dist: uvicorn
Requires-Dist: sqlalchemy
Requires-Dist: jinja2
Requires-Dist: pyyaml
